<?xml version="1.0" encoding="UTF-8"?>
<sbml xmlns="http://www.sbml.org/sbml/level3/version1/core" xmlns:layout="http://www.sbml.org/sbml/level3/version1/layout/version1" xmlns:render="http://www.sbml.org/sbml/level3/version1/render/version1" level="3" version="1" layout:required="false" render:required="false">
  <model id="__main">
    <listOfCompartments>
      <compartment sboTerm="SBO:0000410" id="graphfab_default_compartment" size="1" constant="false"/>
    </listOfCompartments>
    <listOfSpecies>
      <species id="X0" compartment="graphfab_default_compartment" initialConcentration="0" hasOnlySubstanceUnits="false" boundaryCondition="false" constant="false"/>
      <species id="A" compartment="graphfab_default_compartment" initialConcentration="0" hasOnlySubstanceUnits="false" boundaryCondition="false" constant="false"/>
      <species id="B" compartment="graphfab_default_compartment" initialConcentration="0" hasOnlySubstanceUnits="false" boundaryCondition="false" constant="false"/>
      <species id="D" compartment="graphfab_default_compartment" initialConcentration="0" hasOnlySubstanceUnits="false" boundaryCondition="false" constant="false"/>
      <species id="C" compartment="graphfab_default_compartment" initialConcentration="0" hasOnlySubstanceUnits="false" boundaryCondition="false" constant="false"/>
      <species id="X1" compartment="graphfab_default_compartment" initialConcentration="0" hasOnlySubstanceUnits="false" boundaryCondition="false" constant="false"/>
    </listOfSpecies>
    <listOfReactions>
      <reaction id="_J0" reversible="false" fast="false">
        <listOfReactants>
          <speciesReference species="X0" stoichiometry="1" constant="false"/>
        </listOfReactants>
        <listOfProducts>
          <speciesReference species="A" stoichiometry="1" constant="false"/>
        </listOfProducts>
        <kineticLaw>
          <math xmlns="http://www.w3.org/1998/Math/MathML">
            <cn type="integer"> 1 </cn>
          </math>
        </kineticLaw>
      </reaction>
      <reaction id="_J1" reversible="false" fast="false">
        <listOfReactants>
          <speciesReference species="A" stoichiometry="1" constant="false"/>
        </listOfReactants>
        <listOfProducts>
          <speciesReference species="B" stoichiometry="1" constant="false"/>
        </listOfProducts>
        <kineticLaw>
          <math xmlns="http://www.w3.org/1998/Math/MathML">
            <cn type="integer"> 1 </cn>
          </math>
        </kineticLaw>
      </reaction>
      <reaction id="_J2" reversible="false" fast="false">
        <listOfReactants>
          <speciesReference species="B" stoichiometry="1" constant="false"/>
        </listOfReactants>
        <listOfProducts>
          <speciesReference species="D" stoichiometry="1" constant="false"/>
        </listOfProducts>
        <kineticLaw>
          <math xmlns="http://www.w3.org/1998/Math/MathML">
            <cn type="integer"> 1 </cn>
          </math>
        </kineticLaw>
      </reaction>
      <reaction id="_J3" reversible="false" fast="false">
        <listOfReactants>
          <speciesReference species="A" stoichiometry="1" constant="false"/>
        </listOfReactants>
        <listOfProducts>
          <speciesReference species="C" stoichiometry="1" constant="false"/>
        </listOfProducts>
        <kineticLaw>
          <math xmlns="http://www.w3.org/1998/Math/MathML">
            <cn type="integer"> 1 </cn>
          </math>
        </kineticLaw>
      </reaction>
      <reaction id="_J4" reversible="false" fast="false">
        <listOfReactants>
          <speciesReference species="C" stoichiometry="1" constant="false"/>
        </listOfReactants>
        <listOfProducts>
          <speciesReference species="D" stoichiometry="1" constant="false"/>
        </listOfProducts>
        <kineticLaw>
          <math xmlns="http://www.w3.org/1998/Math/MathML">
            <cn type="integer"> 1 </cn>
          </math>
        </kineticLaw>
      </reaction>
      <reaction id="_J5" reversible="false" fast="false">
        <listOfReactants>
          <speciesReference species="D" stoichiometry="1" constant="false"/>
        </listOfReactants>
        <listOfProducts>
          <speciesReference species="X1" stoichiometry="1" constant="false"/>
        </listOfProducts>
        <kineticLaw>
          <math xmlns="http://www.w3.org/1998/Math/MathML">
            <cn type="integer"> 1 </cn>
          </math>
        </kineticLaw>
      </reaction>
    </listOfReactions>
    <layout:listOfLayouts xmlns:xsi="http://www.w3.org/2001/XMLSchema-instance" xmlns:layout="http://www.sbml.org/sbml/level3/version1/layout/version1">
      <layout:layout layout:id="Graphfab_Layout">
        <layout:dimensions layout:width="1024" layout:height="1024"/>
        <layout:listOfSpeciesGlyphs>
          <layout:speciesGlyph layout:id="X0_Glyph" layout:species="X0">
            <layout:boundingBox>
              <layout:position layout:x="0" layout:y="327"/>
              <layout:dimensions layout:width="40" layout:height="20"/>
            </layout:boundingBox>
          </layout:speciesGlyph>
          <layout:speciesGlyph layout:id="A_Glyph" layout:species="A">
            <layout:boundingBox>
              <layout:position layout:x="126" layout:y="243"/>
              <layout:dimensions layout:width="30" layout:height="20"/>
            </layout:boundingBox>
          </layout:speciesGlyph>
          <layout:speciesGlyph layout:id="B_Glyph" layout:species="B">
            <layout:boundingBox>
              <layout:position layout:x="278" layout:y="219"/>
              <layout:dimensions layout:width="30" layout:height="20"/>
            </layout:boundingBox>
          </layout:speciesGlyph>
          <layout:speciesGlyph layout:id="D_Glyph" layout:species="D">
            <layout:boundingBox>
              <layout:position layout:x="354" layout:y="84"/>
              <layout:dimensions layout:width="30" layout:height="20"/>
            </layout:boundingBox>
          </layout:speciesGlyph>
          <layout:speciesGlyph layout:id="C_Glyph" layout:species="C">
            <layout:boundingBox>
              <layout:position layout:x="201" layout:y="108"/>
              <layout:dimensions layout:width="30" layout:height="20"/>
            </layout:boundingBox>
          </layout:speciesGlyph>
          <layout:speciesGlyph layout:id="X1_Glyph" layout:species="X1">
            <layout:boundingBox>
              <layout:position layout:x="470" layout:y="0"/>
              <layout:dimensions layout:width="40" layout:height="20"/>
            </layout:boundingBox>
          </layout:speciesGlyph>
        </layout:listOfSpeciesGlyphs>
        <layout:listOfReactionGlyphs>
          <layout:reactionGlyph layout:id="_J0_Glyph" layout:reaction="_J0">
            <layout:boundingBox>
              <layout:position layout:x="0" layout:y="0"/>
              <layout:dimensions layout:width="0" layout:height="0"/>
            </layout:boundingBox>
            <layout:listOfSpeciesReferenceGlyphs>
              <layout:speciesReferenceGlyph layout:id="_J0_SpeciesRef1" layout:speciesReference="X0" layout:speciesGlyph="X0_Glyph" layout:role="substrate">
                <layout:curve>
                  <layout:listOfCurveSegments>
                    <layout:curveSegment xmlns:xsi="http://www.w3.org/2001/XMLSchema-instance" xsi:type="CubicBezier">
                      <layout:start layout:x="41.9821908420059" layout:y="321.059052700663"/>
                      <layout:end layout:x="76.9333561787275" layout:y="297.365777213646"/>
                      <layout:basePoint1 layout:x="58.5368953489237" layout:y="309.836675114401"/>
                      <layout:basePoint2 layout:x="56.1608088381438" layout:y="311.276250857027"/>
                    </layout:curveSegment>
                  </layout:listOfCurveSegments>
                </layout:curve>
              </layout:speciesReferenceGlyph>
              <layout:speciesReferenceGlyph layout:id="_J0_SpeciesRef2" layout:speciesReference="A" layout:speciesGlyph="A_Glyph" layout:role="product">
                <layout:curve>
                  <layout:listOfCurveSegments>
                    <layout:curveSegment xmlns:xsi="http://www.w3.org/2001/XMLSchema-instance" xsi:type="CubicBezier">
                      <layout:start layout:x="76.9333561787275" layout:y="297.365777213646"/>
                      <layout:end layout:x="118.742429781841" layout:y="267.726326845763"/>
                      <layout:basePoint1 layout:x="97.7059035193113" layout:y="283.455303570265"/>
                      <layout:basePoint2 layout:x="102.426486118893" layout:y="279.293088812169"/>
                    </layout:curveSegment>
                  </layout:listOfCurveSegments>
                </layout:curve>
              </layout:speciesReferenceGlyph>
            </layout:listOfSpeciesReferenceGlyphs>
          </layout:reactionGlyph>
          <layout:reactionGlyph layout:id="_J1_Glyph" layout:reaction="_J1">
            <layout:boundingBox>
              <layout:position layout:x="0" layout:y="0"/>
              <layout:dimensions layout:width="0" layout:height="0"/>
            </layout:boundingBox>
            <layout:listOfSpeciesReferenceGlyphs>
              <layout:speciesReferenceGlyph layout:id="_J1_SpeciesRef1" layout:speciesReference="A" layout:speciesGlyph="A_Glyph" layout:role="substrate">
                <layout:curve>
                  <layout:listOfCurveSegments>
                    <layout:curveSegment xmlns:xsi="http://www.w3.org/2001/XMLSchema-instance" xsi:type="CubicBezier">
                      <layout:start layout:x="165.751268215932" layout:y="252.742210403076"/>
                      <layout:end layout:x="218.078067480174" layout:y="248.926653810612"/>
                      <layout:basePoint1 layout:x="185.698309212632" layout:y="251.287715481826"/>
                      <layout:basePoint2 layout:x="193.372695451502" layout:y="252.753479247566"/>
                    </layout:curveSegment>
                  </layout:listOfCurveSegments>
                </layout:curve>
              </layout:speciesReferenceGlyph>
              <layout:speciesReferenceGlyph layout:id="_J1_SpeciesRef2" layout:speciesReference="B" layout:speciesGlyph="B_Glyph" layout:role="product">
                <layout:curve>
                  <layout:listOfCurveSegments>
                    <layout:curveSegment xmlns:xsi="http://www.w3.org/2001/XMLSchema-instance" xsi:type="CubicBezier">
                      <layout:start layout:x="218.078067480174" layout:y="248.926653810612"/>
                      <layout:end layout:x="268.240700781063" layout:y="236.828291046243"/>
                      <layout:basePoint1 layout:x="242.783439508846" layout:y="245.099828373657"/>
                      <layout:basePoint2 layout:x="248.798185351448" layout:y="241.517490740134"/>
                    </layout:curveSegment>
                  </layout:listOfCurveSegments>
                </layout:curve>
              </layout:speciesReferenceGlyph>
            </layout:listOfSpeciesReferenceGlyphs>
          </layout:reactionGlyph>
          <layout:reactionGlyph layout:id="_J2_Glyph" layout:reaction="_J2">
            <layout:boundingBox>
              <layout:position layout:x="0" layout:y="0"/>
              <layout:dimensions layout:width="0" layout:height="0"/>
            </layout:boundingBox>
            <layout:listOfSpeciesReferenceGlyphs>
              <layout:speciesReferenceGlyph layout:id="_J2_SpeciesRef1" layout:speciesReference="B" layout:speciesGlyph="B_Glyph" layout:role="substrate">
                <layout:curve>
                  <layout:listOfCurveSegments>
                    <layout:curveSegment xmlns:xsi="http://www.w3.org/2001/XMLSchema-instance" xsi:type="CubicBezier">
                      <layout:start layout:x="306.992842383167" layout:y="210.925143883788"/>
                      <layout:end layout:x="338.058022162985" layout:y="165.488371944075"/>
                      <layout:basePoint1 layout:x="318.28079342881" layout:y="194.4150814614"/>
                      <layout:basePoint2 layout:x="325.858518171761" layout:y="187.309739966455"/>
                    </layout:curveSegment>
                  </layout:listOfCurveSegments>
                </layout:curve>
              </layout:speciesReferenceGlyph>
              <layout:speciesReferenceGlyph layout:id="_J2_SpeciesRef2" layout:speciesReference="D" layout:speciesGlyph="D_Glyph" layout:role="product">
                <layout:curve>
                  <layout:listOfCurveSegments>
                    <layout:curveSegment xmlns:xsi="http://www.w3.org/2001/XMLSchema-instance" xsi:type="CubicBezier">
                      <layout:start layout:x="338.058022162985" layout:y="165.488371944075"/>
                      <layout:end layout:x="360.549702485377" layout:y="113.211776814958"/>
                      <layout:basePoint1 layout:x="350.257526154209" layout:y="143.667003921696"/>
                      <layout:basePoint2 layout:x="352.645367727354" layout:y="131.583534815572"/>
                    </layout:curveSegment>
                  </layout:listOfCurveSegments>
                </layout:curve>
              </layout:speciesReferenceGlyph>
            </layout:listOfSpeciesReferenceGlyphs>
          </layout:reactionGlyph>
          <layout:reactionGlyph layout:id="_J3_Glyph" layout:reaction="_J3">
            <layout:boundingBox>
              <layout:position layout:x="0" layout:y="0"/>
              <layout:dimensions layout:width="0" layout:height="0"/>
            </layout:boundingBox>
            <layout:listOfSpeciesReferenceGlyphs>
              <layout:speciesReferenceGlyph layout:id="_J3_SpeciesRef1" layout:speciesReference="A" layout:speciesGlyph="A_Glyph" layout:role="substrate">
                <layout:curve>
                  <layout:listOfCurveSegments>
                    <layout:curveSegment xmlns:xsi="http://www.w3.org/2001/XMLSchema-instance" xsi:type="CubicBezier">
                      <layout:start layout:x="147.528642750828" layout:y="232.4790028402"/>
                      <layout:end layout:x="171.570822267392" layout:y="181.578613688832"/>
                      <layout:basePoint1 layout:x="156.070478336051" layout:y="214.394837257154"/>
                      <layout:basePoint2 layout:x="159.387984910685" layout:y="203.409291047541"/>
                    </layout:curveSegment>
                  </layout:listOfCurveSegments>
                </layout:curve>
              </layout:speciesReferenceGlyph>
              <layout:speciesReferenceGlyph layout:id="_J3_SpeciesRef2" layout:speciesReference="C" layout:speciesGlyph="C_Glyph" layout:role="product">
                <layout:curve>
                  <layout:listOfCurveSegments>
                    <layout:curveSegment xmlns:xsi="http://www.w3.org/2001/XMLSchema-instance" xsi:type="CubicBezier">
                      <layout:start layout:x="171.570822267392" layout:y="181.578613688832"/>
                      <layout:end layout:x="201.752828085252" layout:y="135.739299696552"/>
                      <layout:basePoint1 layout:x="183.753659624099" layout:y="159.747936330124"/>
                      <layout:basePoint2 layout:x="190.754251904591" layout:y="152.44353035822"/>
                    </layout:curveSegment>
                  </layout:listOfCurveSegments>
                </layout:curve>
              </layout:speciesReferenceGlyph>
            </layout:listOfSpeciesReferenceGlyphs>
          </layout:reactionGlyph>
          <layout:reactionGlyph layout:id="_J4_Glyph" layout:reaction="_J4">
            <layout:boundingBox>
              <layout:position layout:x="0" layout:y="0"/>
              <layout:dimensions layout:width="0" layout:height="0"/>
            </layout:boundingBox>
            <layout:listOfSpeciesReferenceGlyphs>
              <layout:speciesReferenceGlyph layout:id="_J4_SpeciesRef1" layout:speciesReference="C" layout:speciesGlyph="C_Glyph" layout:role="substrate">
                <layout:curve>
                  <layout:listOfCurveSegments>
                    <layout:curveSegment xmlns:xsi="http://www.w3.org/2001/XMLSchema-instance" xsi:type="CubicBezier">
                      <layout:start layout:x="240.351934554096" layout:y="109.94041340034"/>
                      <layout:end layout:x="291.232424426749" layout:y="98.4750508248293"/>
                      <layout:basePoint1 layout:x="259.862711866881" layout:y="105.543872868183"/>
                      <layout:basePoint2 layout:x="266.528667147612" layout:y="102.312286326263"/>
                    </layout:curveSegment>
                  </layout:listOfCurveSegments>
                </layout:curve>
              </layout:speciesReferenceGlyph>
              <layout:speciesReferenceGlyph layout:id="_J4_SpeciesRef2" layout:speciesReference="D" layout:speciesGlyph="D_Glyph" layout:role="product">
                <layout:curve>
                  <layout:listOfCurveSegments>
                    <layout:curveSegment xmlns:xsi="http://www.w3.org/2001/XMLSchema-instance" xsi:type="CubicBezier">
                      <layout:start layout:x="291.232424426749" layout:y="98.4750508248293"/>
                      <layout:end layout:x="342.75425377437" layout:y="93.9824370535198"/>
                      <layout:basePoint1 layout:x="315.936181705887" layout:y="94.6378153233961"/>
                      <layout:basePoint2 layout:x="322.829858262517" layout:y="95.7198096351031"/>
                    </layout:curveSegment>
                  </layout:listOfCurveSegments>
                </layout:curve>
              </layout:speciesReferenceGlyph>
            </layout:listOfSpeciesReferenceGlyphs>
          </layout:reactionGlyph>
          <layout:reactionGlyph layout:id="_J5_Glyph" layout:reaction="_J5">
            <layout:boundingBox>
              <layout:position layout:x="0" layout:y="0"/>
              <layout:dimensions layout:width="0" layout:height="0"/>
            </layout:boundingBox>
            <layout:listOfSpeciesReferenceGlyphs>
              <layout:speciesReferenceGlyph layout:id="_J5_SpeciesRef1" layout:speciesReference="D" layout:speciesGlyph="D_Glyph" layout:role="substrate">
                <layout:curve>
                  <layout:listOfCurveSegments>
                    <layout:curveSegment xmlns:xsi="http://www.w3.org/2001/XMLSchema-instance" xsi:type="CubicBezier">
                      <layout:start layout:x="391.147382099873" layout:y="78.3062538512399"/>
                      <layout:end layout:x="432.859515726951" layout:y="49.725922391831"/>
                      <layout:basePoint1 layout:x="407.646067270313" layout:y="67.0016801022355"/>
                      <layout:basePoint2 layout:x="412.626603271336" layout:y="64.4102423816512"/>
                    </layout:curveSegment>
                  </layout:listOfCurveSegments>
                </layout:curve>
              </layout:speciesReferenceGlyph>
              <layout:speciesReferenceGlyph layout:id="_J5_SpeciesRef2" layout:speciesReference="X1" layout:speciesGlyph="X1_Glyph" layout:role="product">
                <layout:curve>
                  <layout:listOfCurveSegments>
                    <layout:curveSegment xmlns:xsi="http://www.w3.org/2001/XMLSchema-instance" xsi:type="CubicBezier">
                      <layout:start layout:x="432.859515726951" layout:y="49.725922391831"/>
                      <layout:end layout:x="466.584234422749" layout:y="25.5087064875909"/>
                      <layout:basePoint1 layout:x="453.092428182565" layout:y="35.0416024020109"/>
                      <layout:basePoint2 layout:x="450.338808978156" layout:y="37.1743034343476"/>
                    </layout:curveSegment>
                  </layout:listOfCurveSegments>
                </layout:curve>
              </layout:speciesReferenceGlyph>
            </layout:listOfSpeciesReferenceGlyphs>
          </layout:reactionGlyph>
        </layout:listOfReactionGlyphs>
        <layout:listOfTextGlyphs>
          <layout:textGlyph layout:id="tX0_Glyph" layout:text="X0" layout:graphicalObject="X0_Glyph">
            <layout:boundingBox>
              <layout:position layout:x="0" layout:y="327"/>
              <layout:dimensions layout:width="40" layout:height="20"/>
            </layout:boundingBox>
          </layout:textGlyph>
          <layout:textGlyph layout:id="tA_Glyph" layout:text="A" layout:graphicalObject="A_Glyph">
            <layout:boundingBox>
              <layout:position layout:x="126" layout:y="243"/>
              <layout:dimensions layout:width="30" layout:height="20"/>
            </layout:boundingBox>
          </layout:textGlyph>
          <layout:textGlyph layout:id="tB_Glyph" layout:text="B" layout:graphicalObject="B_Glyph">
            <layout:boundingBox>
              <layout:position layout:x="278" layout:y="219"/>
              <layout:dimensions layout:width="30" layout:height="20"/>
            </layout:boundingBox>
          </layout:textGlyph>
          <layout:textGlyph layout:id="tD_Glyph" layout:text="D" layout:graphicalObject="D_Glyph">
            <layout:boundingBox>
              <layout:position layout:x="354" layout:y="84"/>
              <layout:dimensions layout:width="30" layout:height="20"/>
            </layout:boundingBox>
          </layout:textGlyph>
          <layout:textGlyph layout:id="tC_Glyph" layout:text="C" layout:graphicalObject="C_Glyph">
            <layout:boundingBox>
              <layout:position layout:x="201" layout:y="108"/>
              <layout:dimensions layout:width="30" layout:height="20"/>
            </layout:boundingBox>
          </layout:textGlyph>
          <layout:textGlyph layout:id="tX1_Glyph" layout:text="X1" layout:graphicalObject="X1_Glyph">
            <layout:boundingBox>
              <layout:position layout:x="470" layout:y="0"/>
              <layout:dimensions layout:width="40" layout:height="20"/>
            </layout:boundingBox>
          </layout:textGlyph>
        </layout:listOfTextGlyphs>
        <render:listOfRenderInformation xmlns:render="http://www.sbml.org/sbml/level3/version1/render/version1">
          <render:renderInformation render:id="localRenderInfo" render:name="Fill_Color Render Information">
            <render:listOfStyles>
              <render:style render:idList="X0_Glyph">
                <render:g render:stroke="#0000ff" render:stroke-width="1" render:fill="#c9e0fb">
                  <render:rectangle render:stroke="#0000ff" render:stroke-width="1" render:fill="#c9e0fb" render:x="0" render:y="0" render:width="100%" render:height="100%"/>
                </render:g>
              </render:style>
              <render:style render:idList="tX0_Glyph">
                <render:g render:stroke="#000000" render:font-family="Arial" render:font-style="normal" render:text-anchor="middle" render:vtext-anchor="top" render:font-size="10"/>
              </render:style>
              <render:style render:idList="A_Glyph">
                <render:g render:stroke="#0000ff" render:stroke-width="1" render:fill="#c9e0fb">
                  <render:rectangle render:stroke="#0000ff" render:stroke-width="1" render:fill="#c9e0fb" render:x="0" render:y="0" render:width="100%" render:height="100%"/>
                </render:g>
              </render:style>
              <render:style render:idList="tA_Glyph">
                <render:g render:stroke="#000000" render:font-family="Arial" render:font-style="normal" render:text-anchor="middle" render:vtext-anchor="top" render:font-size="10"/>
              </render:style>
              <render:style render:idList="B_Glyph">
                <render:g render:stroke="#0000ff" render:stroke-width="1" render:fill="#c9e0fb">
                  <render:rectangle render:stroke="#0000ff" render:stroke-width="1" render:fill="#c9e0fb" render:x="0" render:y="0" render:width="100%" render:height="100%"/>
                </render:g>
              </render:style>
              <render:style render:idList="tB_Glyph">
                <render:g render:stroke="#000000" render:font-family="Arial" render:font-style="normal" render:text-anchor="middle" render:vtext-anchor="top" render:font-size="10"/>
              </render:style>
              <render:style render:idList="D_Glyph">
                <render:g render:stroke="#0000ff" render:stroke-width="1" render:fill="#c9e0fb">
                  <render:rectangle render:stroke="#0000ff" render:stroke-width="1" render:fill="#c9e0fb" render:x="0" render:y="0" render:width="100%" render:height="100%"/>
                </render:g>
              </render:style>
              <render:style render:idList="tD_Glyph">
                <render:g render:stroke="#000000" render:font-family="Arial" render:font-style="normal" render:text-anchor="middle" render:vtext-anchor="top" render:font-size="10"/>
              </render:style>
              <render:style render:idList="C_Glyph">
                <render:g render:stroke="#0000ff" render:stroke-width="1" render:fill="#c9e0fb">
                  <render:rectangle render:stroke="#0000ff" render:stroke-width="1" render:fill="#c9e0fb" render:x="0" render:y="0" render:width="100%" render:height="100%"/>
                </render:g>
              </render:style>
              <render:style render:idList="tC_Glyph">
                <render:g render:stroke="#000000" render:font-family="Arial" render:font-style="normal" render:text-anchor="middle" render:vtext-anchor="top" render:font-size="10"/>
              </render:style>
              <render:style render:idList="X1_Glyph">
                <render:g render:stroke="#0000ff" render:stroke-width="1" render:fill="#c9e0fb">
                  <render:rectangle render:stroke="#0000ff" render:stroke-width="1" render:fill="#c9e0fb" render:x="0" render:y="0" render:width="100%" render:height="100%"/>
                </render:g>
              </render:style>
              <render:style render:idList="tX1_Glyph">
                <render:g render:stroke="#000000" render:font-family="Arial" render:font-style="normal" render:text-anchor="middle" render:vtext-anchor="top" render:font-size="10"/>
              </render:style>
              <render:style render:idList="_J0">
                <render:g render:stroke="#0000ff" render:stroke-width="1" render:fill="#0000ff"/>
              </render:style>
              <render:style render:idList="_J1">
                <render:g render:stroke="#0000ff" render:stroke-width="1" render:fill="#0000ff"/>
              </render:style>
              <render:style render:idList="_J2">
                <render:g render:stroke="#0000ff" render:stroke-width="1" render:fill="#0000ff"/>
              </render:style>
              <render:style render:idList="_J3">
                <render:g render:stroke="#0000ff" render:stroke-width="1" render:fill="#0000ff"/>
              </render:style>
              <render:style render:idList="_J4">
                <render:g render:stroke="#0000ff" render:stroke-width="1" render:fill="#0000ff"/>
              </render:style>
              <render:style render:idList="_J5">
                <render:g render:stroke="#0000ff" render:stroke-width="1" render:fill="#0000ff"/>
              </render:style>
              <render:style render:roleList="product">
                <render:g render:endHead="product"/>
              </render:style>
            </render:listOfStyles>
          </render:renderInformation>
        </render:listOfRenderInformation>
      </layout:layout>
    </layout:listOfLayouts>
  </model>
</sbml>
