<?xml version="1.0" encoding="UTF-8"?>
<sbml xmlns="http://www.sbml.org/sbml/level3/version1/core" xmlns:layout="http://www.sbml.org/sbml/level3/version1/layout/version1" xmlns:render="http://www.sbml.org/sbml/level3/version1/render/version1" level="3" version="1" layout:required="false" render:required="false">
  <model id="__main">
    <listOfCompartments>
      <compartment sboTerm="SBO:0000410" id="graphfab_default_compartment" size="1" constant="false"/>
    </listOfCompartments>
    <listOfSpecies>
      <species id="X0" compartment="graphfab_default_compartment" initialConcentration="0" hasOnlySubstanceUnits="false" boundaryCondition="false" constant="false"/>
      <species id="A" compartment="graphfab_default_compartment" initialConcentration="0" hasOnlySubstanceUnits="false" boundaryCondition="false" constant="false"/>
      <species id="B" compartment="graphfab_default_compartment" initialConcentration="0" hasOnlySubstanceUnits="false" boundaryCondition="false" constant="false"/>
      <species id="D" compartment="graphfab_default_compartment" initialConcentration="0" hasOnlySubstanceUnits="false" boundaryCondition="false" constant="false"/>
      <species id="C" compartment="graphfab_default_compartment" initialConcentration="0" hasOnlySubstanceUnits="false" boundaryCondition="false" constant="false"/>
      <species id="X1" compartment="graphfab_default_compartment" initialConcentration="0" hasOnlySubstanceUnits="false" boundaryCondition="false" constant="false"/>
    </listOfSpecies>
    <listOfReactions>
      <reaction id="_J0" reversible="false" fast="false">
        <listOfReactants>
          <speciesReference species="X0" stoichiometry="1" constant="false"/>
        </listOfReactants>
        <listOfProducts>
          <speciesReference species="A" stoichiometry="1" constant="false"/>
        </listOfProducts>
        <kineticLaw>
          <math xmlns="http://www.w3.org/1998/Math/MathML">
            <cn type="integer"> 1 </cn>
          </math>
        </kineticLaw>
      </reaction>
      <reaction id="_J1" reversible="false" fast="false">
        <listOfReactants>
          <speciesReference species="A" stoichiometry="1" constant="false"/>
        </listOfReactants>
        <listOfProducts>
          <speciesReference species="B" stoichiometry="1" constant="false"/>
        </listOfProducts>
        <kineticLaw>
          <math xmlns="http://www.w3.org/1998/Math/MathML">
            <cn type="integer"> 1 </cn>
          </math>
        </kineticLaw>
      </reaction>
      <reaction id="_J2" reversible="false" fast="false">
        <listOfReactants>
          <speciesReference species="B" stoichiometry="1" constant="false"/>
        </listOfReactants>
        <listOfProducts>
          <speciesReference species="D" stoichiometry="1" constant="false"/>
        </listOfProducts>
        <kineticLaw>
          <math xmlns="http://www.w3.org/1998/Math/MathML">
            <cn type="integer"> 1 </cn>
          </math>
        </kineticLaw>
      </reaction>
      <reaction id="_J3" reversible="false" fast="false">
        <listOfReactants>
          <speciesReference species="A" stoichiometry="1" constant="false"/>
        </listOfReactants>
        <listOfProducts>
          <speciesReference species="C" stoichiometry="1" constant="false"/>
        </listOfProducts>
        <kineticLaw>
          <math xmlns="http://www.w3.org/1998/Math/MathML">
            <cn type="integer"> 1 </cn>
          </math>
        </kineticLaw>
      </reaction>
      <reaction id="_J4" reversible="false" fast="false">
        <listOfReactants>
          <speciesReference species="C" stoichiometry="1" constant="false"/>
        </listOfReactants>
        <listOfProducts>
          <speciesReference species="D" stoichiometry="1" constant="false"/>
        </listOfProducts>
        <kineticLaw>
          <math xmlns="http://www.w3.org/1998/Math/MathML">
            <cn type="integer"> 1 </cn>
          </math>
        </kineticLaw>
      </reaction>
      <reaction id="_J5" reversible="false" fast="false">
        <listOfReactants>
          <speciesReference species="D" stoichiometry="1" constant="false"/>
        </listOfReactants>
        <listOfProducts>
          <speciesReference species="X1" stoichiometry="1" constant="false"/>
        </listOfProducts>
        <kineticLaw>
          <math xmlns="http://www.w3.org/1998/Math/MathML">
            <cn type="integer"> 1 </cn>
          </math>
        </kineticLaw>
      </reaction>
    </listOfReactions>
    <layout:listOfLayouts xmlns:xsi="http://www.w3.org/2001/XMLSchema-instance" xmlns:layout="http://www.sbml.org/sbml/level3/version1/layout/version1">
      <layout:layout layout:id="Graphfab_Layout">
        <layout:dimensions layout:width="1024" layout:height="1024"/>
        <layout:listOfSpeciesGlyphs>
          <layout:speciesGlyph layout:id="X0_Glyph" layout:species="X0">
            <layout:boundingBox>
              <layout:position layout:x="489" layout:y="346"/>
              <layout:dimensions layout:width="48" layout:height="24"/>
            </layout:boundingBox>
          </layout:speciesGlyph>
          <layout:speciesGlyph layout:id="A_Glyph" layout:species="A">
            <layout:boundingBox>
              <layout:position layout:x="368" layout:y="256"/>
              <layout:dimensions layout:width="36" layout:height="24"/>
            </layout:boundingBox>
          </layout:speciesGlyph>
          <layout:speciesGlyph layout:id="B_Glyph" layout:species="B">
            <layout:boundingBox>
              <layout:position layout:x="210" layout:y="229"/>
              <layout:dimensions layout:width="36" layout:height="24"/>
            </layout:boundingBox>
          </layout:speciesGlyph>
          <layout:speciesGlyph layout:id="D_Glyph" layout:species="D">
            <layout:boundingBox>
              <layout:position layout:x="132" layout:y="89"/>
              <layout:dimensions layout:width="36" layout:height="24"/>
            </layout:boundingBox>
          </layout:speciesGlyph>
          <layout:speciesGlyph layout:id="C_Glyph" layout:species="C">
            <layout:boundingBox>
              <layout:position layout:x="290" layout:y="116"/>
              <layout:dimensions layout:width="36" layout:height="24"/>
            </layout:boundingBox>
          </layout:speciesGlyph>
          <layout:speciesGlyph layout:id="X1_Glyph" layout:species="X1">
            <layout:boundingBox>
              <layout:position layout:x="0" layout:y="0"/>
              <layout:dimensions layout:width="48" layout:height="24"/>
            </layout:boundingBox>
          </layout:speciesGlyph>
        </layout:listOfSpeciesGlyphs>
        <layout:listOfReactionGlyphs>
          <layout:reactionGlyph layout:id="_J0_Glyph" layout:reaction="_J0">
            <layout:boundingBox>
              <layout:position layout:x="0" layout:y="0"/>
              <layout:dimensions layout:width="0" layout:height="0"/>
            </layout:boundingBox>
            <layout:listOfSpeciesReferenceGlyphs>
              <layout:speciesReferenceGlyph layout:id="_J0_SpeciesRef1" layout:speciesReference="X0" layout:speciesGlyph="X0_Glyph" layout:role="substrate">
                <layout:curve>
                  <layout:listOfCurveSegments>
                    <layout:curveSegment xmlns:xsi="http://www.w3.org/2001/XMLSchema-instance" xsi:type="CubicBezier">
                      <layout:start layout:x="486.53202429462" layout:y="339.121432370385"/>
                      <layout:end layout:x="453.060902016649" layout:y="315.256990452256"/>
                      <layout:basePoint1 layout:x="470.247350307502" layout:y="327.510687642622"/>
                      <layout:basePoint2 layout:x="473.141416830527" layout:y="330.149032783973"/>
                    </layout:curveSegment>
                  </layout:listOfCurveSegments>
                </layout:curve>
              </layout:speciesReferenceGlyph>
              <layout:speciesReferenceGlyph layout:id="_J0_SpeciesRef2" layout:speciesReference="A" layout:speciesGlyph="A_Glyph" layout:role="product">
                <layout:curve>
                  <layout:listOfCurveSegments>
                    <layout:curveSegment xmlns:xsi="http://www.w3.org/2001/XMLSchema-instance" xsi:type="CubicBezier">
                      <layout:start layout:x="453.060902016649" layout:y="315.256990452256"/>
                      <layout:end layout:x="411.085660091251" layout:y="285.344853593256"/>
                      <layout:basePoint1 layout:x="432.980387202772" layout:y="300.364948120539"/>
                      <layout:basePoint2 layout:x="427.373199190503" layout:y="296.951578802821"/>
                    </layout:curveSegment>
                  </layout:listOfCurveSegments>
                </layout:curve>
              </layout:speciesReferenceGlyph>
            </layout:listOfSpeciesReferenceGlyphs>
          </layout:reactionGlyph>
          <layout:reactionGlyph layout:id="_J1_Glyph" layout:reaction="_J1">
            <layout:boundingBox>
              <layout:position layout:x="0" layout:y="0"/>
              <layout:dimensions layout:width="0" layout:height="0"/>
            </layout:boundingBox>
            <layout:listOfSpeciesReferenceGlyphs>
              <layout:speciesReferenceGlyph layout:id="_J1_SpeciesRef1" layout:speciesReference="A" layout:speciesGlyph="A_Glyph" layout:role="substrate">
                <layout:curve>
                  <layout:listOfCurveSegments>
                    <layout:curveSegment xmlns:xsi="http://www.w3.org/2001/XMLSchema-instance" xsi:type="CubicBezier">
                      <layout:start layout:x="357.839719555272" layout:y="266.625569859092"/>
                      <layout:end layout:x="306.565619938221" layout:y="262.237929772809"/>
                      <layout:basePoint1 layout:x="337.91254593925" layout:y="264.920356770671"/>
                      <layout:basePoint2 layout:x="331.206592860642" layout:y="266.45959454355"/>
                    </layout:curveSegment>
                  </layout:listOfCurveSegments>
                </layout:curve>
              </layout:speciesReferenceGlyph>
              <layout:speciesReferenceGlyph layout:id="_J1_SpeciesRef2" layout:speciesReference="B" layout:speciesGlyph="B_Glyph" layout:role="product">
                <layout:curve>
                  <layout:listOfCurveSegments>
                    <layout:curveSegment xmlns:xsi="http://www.w3.org/2001/XMLSchema-instance" xsi:type="CubicBezier">
                      <layout:start layout:x="306.565619938221" layout:y="262.237929772809"/>
                      <layout:end layout:x="255.380419572685" layout:y="249.683106956717"/>
                      <layout:basePoint1 layout:x="281.924647015801" layout:y="258.016265002067"/>
                      <layout:basePoint2 layout:x="274.804639760388" layout:y="254.4475240354"/>
                    </layout:curveSegment>
                  </layout:listOfCurveSegments>
                </layout:curve>
              </layout:speciesReferenceGlyph>
            </layout:listOfSpeciesReferenceGlyphs>
          </layout:reactionGlyph>
          <layout:reactionGlyph layout:id="_J2_Glyph" layout:reaction="_J2">
            <layout:boundingBox>
              <layout:position layout:x="0" layout:y="0"/>
              <layout:dimensions layout:width="0" layout:height="0"/>
            </layout:boundingBox>
            <layout:listOfSpeciesReferenceGlyphs>
              <layout:speciesReferenceGlyph layout:id="_J2_SpeciesRef1" layout:speciesReference="B" layout:speciesGlyph="B_Glyph" layout:role="substrate">
                <layout:curve>
                  <layout:listOfCurveSegments>
                    <layout:curveSegment xmlns:xsi="http://www.w3.org/2001/XMLSchema-instance" xsi:type="CubicBezier">
                      <layout:start layout:x="212.845335102762" layout:y="220.683533774397"/>
                      <layout:end layout:x="182.631871564629" layout:y="174.831695803154"/>
                      <layout:basePoint1 layout:x="201.840862136284" layout:y="203.983187229189"/>
                      <layout:basePoint2 layout:x="194.844309375261" layout:y="196.645827982121"/>
                    </layout:curveSegment>
                  </layout:listOfCurveSegments>
                </layout:curve>
              </layout:speciesReferenceGlyph>
              <layout:speciesReferenceGlyph layout:id="_J2_SpeciesRef2" layout:speciesReference="D" layout:speciesGlyph="D_Glyph" layout:role="product">
                <layout:curve>
                  <layout:listOfCurveSegments>
                    <layout:curveSegment xmlns:xsi="http://www.w3.org/2001/XMLSchema-instance" xsi:type="CubicBezier">
                      <layout:start layout:x="182.631871564629" layout:y="174.831695803154"/>
                      <layout:end layout:x="157.6418405199" layout:y="121.936801199832"/>
                      <layout:basePoint1 layout:x="170.419433753997" layout:y="153.017563624187"/>
                      <layout:basePoint2 layout:x="166.185289186223" layout:y="140.02020477565"/>
                    </layout:curveSegment>
                  </layout:listOfCurveSegments>
                </layout:curve>
              </layout:speciesReferenceGlyph>
            </layout:listOfSpeciesReferenceGlyphs>
          </layout:reactionGlyph>
          <layout:reactionGlyph layout:id="_J3_Glyph" layout:reaction="_J3">
            <layout:boundingBox>
              <layout:position layout:x="0" layout:y="0"/>
              <layout:dimensions layout:width="0" layout:height="0"/>
            </layout:boundingBox>
            <layout:listOfSpeciesReferenceGlyphs>
              <layout:speciesReferenceGlyph layout:id="_J3_SpeciesRef1" layout:speciesReference="A" layout:speciesGlyph="A_Glyph" layout:role="substrate">
                <layout:curve>
                  <layout:listOfCurveSegments>
                    <layout:curveSegment xmlns:xsi="http://www.w3.org/2001/XMLSchema-instance" xsi:type="CubicBezier">
                      <layout:start layout:x="377.352390452299" layout:y="246.315594030599"/>
                      <layout:end layout:x="354.130708608826" layout:y="194.927797758884"/>
                      <layout:basePoint1 layout:x="369.116446618559" layout:y="228.090083635346"/>
                      <layout:basePoint2 layout:x="366.347959829218" layout:y="216.739234497848"/>
                    </layout:curveSegment>
                  </layout:listOfCurveSegments>
                </layout:curve>
              </layout:speciesReferenceGlyph>
              <layout:speciesReferenceGlyph layout:id="_J3_SpeciesRef2" layout:speciesReference="C" layout:speciesGlyph="C_Glyph" layout:role="product">
                <layout:curve>
                  <layout:listOfCurveSegments>
                    <layout:curveSegment xmlns:xsi="http://www.w3.org/2001/XMLSchema-instance" xsi:type="CubicBezier">
                      <layout:start layout:x="354.130708608826" layout:y="194.927797758884"/>
                      <layout:end layout:x="322.839920067766" layout:y="147.687591741042"/>
                      <layout:basePoint1 layout:x="341.913457388434" layout:y="173.116361019919"/>
                      <layout:basePoint2 layout:x="333.884347935049" layout:y="164.36154187544"/>
                    </layout:curveSegment>
                  </layout:listOfCurveSegments>
                </layout:curve>
              </layout:speciesReferenceGlyph>
            </layout:listOfSpeciesReferenceGlyphs>
          </layout:reactionGlyph>
          <layout:reactionGlyph layout:id="_J4_Glyph" layout:reaction="_J4">
            <layout:boundingBox>
              <layout:position layout:x="0" layout:y="0"/>
              <layout:dimensions layout:width="0" layout:height="0"/>
            </layout:boundingBox>
            <layout:listOfSpeciesReferenceGlyphs>
              <layout:speciesReferenceGlyph layout:id="_J4_SpeciesRef1" layout:speciesReference="C" layout:speciesGlyph="C_Glyph" layout:role="substrate">
                <layout:curve>
                  <layout:listOfCurveSegments>
                    <layout:curveSegment xmlns:xsi="http://www.w3.org/2001/XMLSchema-instance" xsi:type="CubicBezier">
                      <layout:start layout:x="280.23893358623" layout:y="118.889917570216"/>
                      <layout:end layout:x="230.284137611482" layout:y="107.282438591663"/>
                      <layout:basePoint1 layout:x="260.757920285416" layout:y="114.36331611068"/>
                      <layout:basePoint2 layout:x="254.923734814322" layout:y="111.512125303676"/>
                    </layout:curveSegment>
                  </layout:listOfCurveSegments>
                </layout:curve>
              </layout:speciesReferenceGlyph>
              <layout:speciesReferenceGlyph layout:id="_J4_SpeciesRef2" layout:speciesReference="D" layout:speciesGlyph="D_Glyph" layout:role="product">
                <layout:curve>
                  <layout:listOfCurveSegments>
                    <layout:curveSegment xmlns:xsi="http://www.w3.org/2001/XMLSchema-instance" xsi:type="CubicBezier">
                      <layout:start layout:x="230.284137611482" layout:y="107.282438591663"/>
                      <layout:end layout:x="177.833014706924" layout:y="102.048679982882"/>
                      <layout:basePoint1 layout:x="205.644540408641" layout:y="103.05275187965"/>
                      <layout:basePoint2 layout:x="197.734184573818" layout:y="104.034489119994"/>
                    </layout:curveSegment>
                  </layout:listOfCurveSegments>
                </layout:curve>
              </layout:speciesReferenceGlyph>
            </layout:listOfSpeciesReferenceGlyphs>
          </layout:reactionGlyph>
          <layout:reactionGlyph layout:id="_J5_Glyph" layout:reaction="_J5">
            <layout:boundingBox>
              <layout:position layout:x="0" layout:y="0"/>
              <layout:dimensions layout:width="0" layout:height="0"/>
            </layout:boundingBox>
            <layout:listOfSpeciesReferenceGlyphs>
              <layout:speciesReferenceGlyph layout:id="_J5_SpeciesRef1" layout:speciesReference="D" layout:speciesGlyph="D_Glyph" layout:role="substrate">
                <layout:curve>
                  <layout:listOfCurveSegments>
                    <layout:curveSegment xmlns:xsi="http://www.w3.org/2001/XMLSchema-instance" xsi:type="CubicBezier">
                      <layout:start layout:x="124.723959060344" layout:y="82.8451501148057"/>
                      <layout:end layout:x="83.6465185460245" layout:y="54.1954865922641"/>
                      <layout:basePoint1 layout:x="108.31973058079" layout:y="71.4039400393558"/>
                      <layout:basePoint2 layout:x="104.364309627682" layout:y="68.1873818426147"/>
                    </layout:curveSegment>
                  </layout:listOfCurveSegments>
                </layout:curve>
              </layout:speciesReferenceGlyph>
              <layout:speciesReferenceGlyph layout:id="_J5_SpeciesRef2" layout:speciesReference="X1" layout:speciesGlyph="X1_Glyph" layout:role="product">
                <layout:curve>
                  <layout:listOfCurveSegments>
                    <layout:curveSegment xmlns:xsi="http://www.w3.org/2001/XMLSchema-instance" xsi:type="CubicBezier">
                      <layout:start layout:x="83.6465185460245" layout:y="54.1954865922641"/>
                      <layout:end layout:x="47.9729568547162" layout:y="29.5057303640924"/>
                      <layout:basePoint1 layout:x="62.9287274643668" layout:y="40.2035913419135"/>
                      <layout:basePoint2 layout:x="64.4183808624466" layout:y="40.8876471273606"/>
                    </layout:curveSegment>
                  </layout:listOfCurveSegments>
                </layout:curve>
              </layout:speciesReferenceGlyph>
            </layout:listOfSpeciesReferenceGlyphs>
          </layout:reactionGlyph>
        </layout:listOfReactionGlyphs>
        <layout:listOfTextGlyphs>
          <layout:textGlyph layout:id="tX0_Glyph" layout:text="X0" layout:graphicalObject="X0_Glyph">
            <layout:boundingBox>
              <layout:position layout:x="489" layout:y="346"/>
              <layout:dimensions layout:width="48" layout:height="24"/>
            </layout:boundingBox>
          </layout:textGlyph>
          <layout:textGlyph layout:id="tA_Glyph" layout:text="A" layout:graphicalObject="A_Glyph">
            <layout:boundingBox>
              <layout:position layout:x="368" layout:y="256"/>
              <layout:dimensions layout:width="36" layout:height="24"/>
            </layout:boundingBox>
          </layout:textGlyph>
          <layout:textGlyph layout:id="tB_Glyph" layout:text="B" layout:graphicalObject="B_Glyph">
            <layout:boundingBox>
              <layout:position layout:x="210" layout:y="229"/>
              <layout:dimensions layout:width="36" layout:height="24"/>
            </layout:boundingBox>
          </layout:textGlyph>
          <layout:textGlyph layout:id="tD_Glyph" layout:text="D" layout:graphicalObject="D_Glyph">
            <layout:boundingBox>
              <layout:position layout:x="132" layout:y="89"/>
              <layout:dimensions layout:width="36" layout:height="24"/>
            </layout:boundingBox>
          </layout:textGlyph>
          <layout:textGlyph layout:id="tC_Glyph" layout:text="C" layout:graphicalObject="C_Glyph">
            <layout:boundingBox>
              <layout:position layout:x="290" layout:y="116"/>
              <layout:dimensions layout:width="36" layout:height="24"/>
            </layout:boundingBox>
          </layout:textGlyph>
          <layout:textGlyph layout:id="tX1_Glyph" layout:text="X1" layout:graphicalObject="X1_Glyph">
            <layout:boundingBox>
              <layout:position layout:x="0" layout:y="0"/>
              <layout:dimensions layout:width="48" layout:height="24"/>
            </layout:boundingBox>
          </layout:textGlyph>
        </layout:listOfTextGlyphs>
        <render:listOfRenderInformation xmlns:render="http://www.sbml.org/sbml/level3/version1/render/version1">
          <render:renderInformation render:id="localRenderInfo" render:name="Fill_Color Render Information">
            <render:listOfStyles>
              <render:style render:idList="X0_Glyph">
                <render:g render:stroke="#0000ff" render:stroke-width="1" render:fill="#c9e0fb">
                  <render:rectangle render:stroke="#0000ff" render:stroke-width="1" render:fill="#c9e0fb" render:x="0" render:y="0" render:width="100%" render:height="100%"/>
                </render:g>
              </render:style>
              <render:style render:idList="tX0_Glyph">
                <render:g render:stroke="#000000" render:font-family="Arial" render:font-style="normal" render:text-anchor="middle" render:vtext-anchor="top" render:font-size="12"/>
              </render:style>
              <render:style render:idList="A_Glyph">
                <render:g render:stroke="#0000ff" render:stroke-width="1" render:fill="#c9e0fb">
                  <render:rectangle render:stroke="#0000ff" render:stroke-width="1" render:fill="#c9e0fb" render:x="0" render:y="0" render:width="100%" render:height="100%"/>
                </render:g>
              </render:style>
              <render:style render:idList="tA_Glyph">
                <render:g render:stroke="#000000" render:font-family="Arial" render:font-style="normal" render:text-anchor="middle" render:vtext-anchor="top" render:font-size="12"/>
              </render:style>
              <render:style render:idList="B_Glyph">
                <render:g render:stroke="#0000ff" render:stroke-width="1" render:fill="#c9e0fb">
                  <render:rectangle render:stroke="#0000ff" render:stroke-width="1" render:fill="#c9e0fb" render:x="0" render:y="0" render:width="100%" render:height="100%"/>
                </render:g>
              </render:style>
              <render:style render:idList="tB_Glyph">
                <render:g render:stroke="#000000" render:font-family="Arial" render:font-style="normal" render:text-anchor="middle" render:vtext-anchor="top" render:font-size="12"/>
              </render:style>
              <render:style render:idList="D_Glyph">
                <render:g render:stroke="#0000ff" render:stroke-width="1" render:fill="#c9e0fb">
                  <render:rectangle render:stroke="#0000ff" render:stroke-width="1" render:fill="#c9e0fb" render:x="0" render:y="0" render:width="100%" render:height="100%"/>
                </render:g>
              </render:style>
              <render:style render:idList="tD_Glyph">
                <render:g render:stroke="#000000" render:font-family="Arial" render:font-style="normal" render:text-anchor="middle" render:vtext-anchor="top" render:font-size="12"/>
              </render:style>
              <render:style render:idList="C_Glyph">
                <render:g render:stroke="#0000ff" render:stroke-width="1" render:fill="#c9e0fb">
                  <render:rectangle render:stroke="#0000ff" render:stroke-width="1" render:fill="#c9e0fb" render:x="0" render:y="0" render:width="100%" render:height="100%"/>
                </render:g>
              </render:style>
              <render:style render:idList="tC_Glyph">
                <render:g render:stroke="#000000" render:font-family="Arial" render:font-style="normal" render:text-anchor="middle" render:vtext-anchor="top" render:font-size="12"/>
              </render:style>
              <render:style render:idList="X1_Glyph">
                <render:g render:stroke="#0000ff" render:stroke-width="1" render:fill="#c9e0fb">
                  <render:rectangle render:stroke="#0000ff" render:stroke-width="1" render:fill="#c9e0fb" render:x="0" render:y="0" render:width="100%" render:height="100%"/>
                </render:g>
              </render:style>
              <render:style render:idList="tX1_Glyph">
                <render:g render:stroke="#000000" render:font-family="Arial" render:font-style="normal" render:text-anchor="middle" render:vtext-anchor="top" render:font-size="12"/>
              </render:style>
              <render:style render:idList="_J0">
                <render:g render:stroke="blue" render:stroke-width="1" render:fill="blue"/>
              </render:style>
              <render:style render:idList="_J1">
                <render:g render:stroke="blue" render:stroke-width="1" render:fill="blue"/>
              </render:style>
              <render:style render:idList="_J2">
                <render:g render:stroke="blue" render:stroke-width="1" render:fill="blue"/>
              </render:style>
              <render:style render:idList="_J3">
                <render:g render:stroke="blue" render:stroke-width="1" render:fill="blue"/>
              </render:style>
              <render:style render:idList="_J4">
                <render:g render:stroke="blue" render:stroke-width="1" render:fill="blue"/>
              </render:style>
              <render:style render:idList="_J5">
                <render:g render:stroke="blue" render:stroke-width="1" render:fill="blue"/>
              </render:style>
              <render:style render:roleList="product">
                <render:g render:endHead="product"/>
              </render:style>
            </render:listOfStyles>
          </render:renderInformation>
        </render:listOfRenderInformation>
      </layout:layout>
    </layout:listOfLayouts>
  </model>
</sbml>
